zmsai/LDA.py
zmsai/__init__.py
zmsai/__main__.py
zmsai/base.py
zmsai/readData.py
zmsai/utils.py
zmsai/zmsParser.py
zmsai-0.1.5.dist-info/LICENSE
zmsai-0.1.5.dist-info/METADATA
zmsai-0.1.5.dist-info/WHEEL
zmsai-0.1.5.dist-info/entry_points.txt
zmsai-0.1.5.dist-info/top_level.txt
zmsai-0.1.5.dist-info/RECORD
