Metadata-Version: 2.1
Name: zmsai
Version: 0.1.5
Summary: Ai solution for Luhmann's Zettelkasten
Home-page: https://github.com/evi1haxor/zettelkasten-ai/
Author: evi1haxor
Author-email: architdwivedi.off@gmail.com
License: GPLv3
Platform: UNKNOWN
Classifier: Programming Language :: Python :: 3.8
Classifier: License :: OSI Approved :: GNU General Public License v3 (GPLv3)
Classifier: Operating System :: OS Independent
Requires-Dist: scikit-learn
